0lever_so-1.2.0.dist-info/DESCRIPTION.rst
0lever_so-1.2.0.dist-info/METADATA
0lever_so-1.2.0.dist-info/RECORD
0lever_so-1.2.0.dist-info/WHEEL
0lever_so-1.2.0.dist-info/entry_points.txt
0lever_so-1.2.0.dist-info/metadata.json
0lever_so-1.2.0.dist-info/top_level.txt
so/__init__.py
so/so.py
