Metadata-Version: 2.0
Name: 0lever-so
Version: 1.2.0
Summary: 服务器登录工具
Home-page: https://github.com/0lever/so
Author: fqiyou
Author-email: yc.fqiyou@gmail.com
License: UNKNOWN
Platform: UNKNOWN
Requires-Dist: pexpect
Requires-Dist: pyyaml
